CHANGES.rst
CONTRIBUTORS.rst
LICENSE
MANIFEST.in
README.md
pyproject.toml
requirements-dev.txt
requirements.txt
setup.py
gribmagic/__init__.py
gribmagic/commands.py
gribmagic/installer.py
gribmagic/util.py
gribmagic.egg-info/PKG-INFO
gribmagic.egg-info/SOURCES.txt
gribmagic.egg-info/dependency_links.txt
gribmagic.egg-info/entry_points.txt
gribmagic.egg-info/not-zip-safe
gribmagic.egg-info/requires.txt
gribmagic.egg-info/top_level.txt
gribmagic/dwd/__init__.py
gribmagic/dwd/download.py
gribmagic/smith/__init__.py
gribmagic/smith/bbox.py
gribmagic/smith/util.py
gribmagic/smith/regrid/__init__.py
gribmagic/smith/regrid/cli.py
gribmagic/smith/regrid/engine.py
gribmagic/smith/regrid/model.py
gribmagic/unity/__init__.py
gribmagic/unity/core.py
gribmagic/unity/enumerations.py
gribmagic/unity/exceptions.py
gribmagic/unity/model.py
gribmagic/unity/reader.py
gribmagic/unity/configuration/__init__.py
gribmagic/unity/configuration/constants.py
gribmagic/unity/configuration/model.py
gribmagic/unity/configuration/parser.py
gribmagic/unity/download/__init__.py
gribmagic/unity/download/decoder.py
gribmagic/unity/download/engine.py
gribmagic/unity/index/__init__.py
gribmagic/unity/index/local.py
gribmagic/unity/index/remote.py
gribmagic/unity/knowledge/__init__.py
gribmagic/unity/knowledge/model_config.yml
gribmagic/unity/knowledge/model_variables_levels_mapping.yml
gribmagic/unity/knowledge/model_variables_mapping.yml
tests/__init__.py
tests/conftest.py
tests/dwd/__init__.py
tests/dwd/recipe_icon_d2_vmax10m.py
tests/dwd/recipe_icon_global_temp2m.py
tests/dwd/recipe_icon_global_temp2m_single.py
tests/dwd/test_pipeline.py
tests/dwd/test_util.py
tests/dwd/util.py
tests/smith/__init__.py
tests/smith/test_bbox_commands.py
tests/smith/test_bbox_units.py
tests/smith/test_regrid_commands.py
tests/smith/test_regrid_units.py
tests/unity/__init__.py
tests/unity/conftest.py
tests/unity/fixtures.py
tests/unity/test_commands.py
tests/unity/test_reader.py
tests/unity/test_util.py
tests/unity/configuration/__init__.py
tests/unity/configuration/test_model.py
tests/unity/configuration/test_parser.py
tests/unity/download/__init__.py
tests/unity/download/test_download.py
tests/unity/download/test_local_store.py
